identixone/__init__.py
identixone/api/__init__.py
identixone/api/client.py
identixone/api/auth/__init__.py
identixone/api/auth/v1/__init__.py
identixone/api/auth/v1/auth.py
identixone/api/entries/__init__.py
identixone/api/entries/v1/__init__.py
identixone/api/entries/v1/entries.py
identixone/api/notifications/__init__.py
identixone/api/notifications/v1/__init__.py
identixone/api/notifications/v1/notifications.py
identixone/api/persons/__init__.py
identixone/api/persons/v1/__init__.py
identixone/api/persons/v1/persons.py
identixone/api/persons_lists/__init__.py
identixone/api/persons_lists/v1/__init__.py
identixone/api/persons_lists/v1/persons_lists.py
identixone/api/sources/__init__.py
identixone/api/sources/v1/__init__.py
identixone/api/sources/v1/sources.py
identixone/api/users/__init__.py
identixone/api/users/v1/__init__.py
identixone/api/users/v1/users.py
identixone/api/utility/__init__.py
identixone/api/utility/v1/__init__.py
identixone/api/utility/v1/utility.py
identixone/base/__init__.py
identixone/base/choices.py
identixone/base/exceptions.py
identixone/http/__init__.py
identixone/http/auth.py
identixone/http/client.py
identixone/utils/__init__.py
identixone/utils/constants.py
identixone/utils/decorators.py
identixone/utils/environment.py
identixone-0.1.6.3.dist-info/AUTHORS.rst
identixone-0.1.6.3.dist-info/LICENSE
identixone-0.1.6.3.dist-info/METADATA
identixone-0.1.6.3.dist-info/WHEEL
identixone-0.1.6.3.dist-info/top_level.txt
identixone-0.1.6.3.dist-info/RECORD
