Metadata-Version: 2.1
Name: identixone
Version: 0.1.6.3
Summary: A Python package for interacting with the Identix.one API
Home-page: https://github.com/identixone/identixone-python
Author: Identix One
Author-email: dev@identix.one
License: MIT license
Keywords: identixone,identix,face,recognition,cloud
Platform: UNKNOWN
Classifier: Development Status :: 2 - Pre-Alpha
Classifier: Intended Audience :: Developers
Classifier: License :: OSI Approved :: MIT License
Classifier: Natural Language :: English
Classifier: Programming Language :: Python
Classifier: Programming Language :: Python :: 3.5
Classifier: Programming Language :: Python :: 3.6
Requires-Dist: requests (>=2.0.0)
